{
  "company": {
    "name": "Nha Khoa Cao Kỳ",
    "logo": "/assets/images/logo.png"
  },
  "navigation": [
    {
      "name": "Giới thiệu",
      "href": "product"
    },
    {
      "name": "Dịch vụ",
      "href": "pricing"
    },
    {
      "name": "Trải nghiệm",
      "href": "features"
    },
    {
      "name": "Về chúng tôi",
      "href": "about"
    }
  ],
  "callToAction": {
    "text": "Liên hệ ngay",
    "href": "tel:0975115379"
  },
  "mainHero": {
    "title": "Cùng bác sĩ chuyên khoa I",
    "subtitle": "Đại học Y Hà Nội",
    "description": "Nguyễn Cao Kỳ - bác sĩ chuyên khoa I ĐH Y Hà Nội với hơn 9 năm kinh nghiệm trong lĩnh vực nha khoa và tham gia các chương trình hội thảo, cập nhật những công nghệ mới nhất, tân tiến nhất từ nước ngoài. Bác sĩ chinh phục khách hàng bằng kỹ thuật chuyên môn tốt, chu đáo tận tình, luôn tư vấn những giải pháp điều trị phù hợp với tài chính của khách. Với phương châm làm việc “Uy tín - Trách nhiệm - Tận tâm, nha khoa Cao Kỳ là địa chỉ chăm sóc sức khỏe răng miệng uy tín, chất lượng cao, được sự tin tưởng và đồng hành của mọi gia đình.",
    "img": "/assets/images/dr_Ky.jpg",
    "primaryAction": {
      "text": "Liên hệ ngay",
      "href": "tel:0975115379"
    },
    "secondaryAction": {
      "text": "Nhắn tin zalo",
      "href": "https://zalo.me/0975115379"
    }
  },
  "product": {
    "title": "Nha Khoa Cao Kỳ",
    "items": [
      {
        "title": "Uy tín - Trách nhiệm - Tận tâm!",
        "description": "Nha Khoa Cao Kỳ - nha khoa dẫn đầu bởi sự phục vụ tận tâm - chuyên môn giỏi - thẩm mĩ cao. Luôn mang tới cho khách hàng những trải nghiệm dịch vụ nha khoa tốt, chất lượng cao, đặt sự an toàn - thẩm mỹ cho khách hàng lên hàng đầu.",
        "img": "/assets/images/product2.jpg"
      }
    ]
  },
  "features": {
    "subtitle": "Trải nghiệm khách hàng: không đau, giá cả hợp lí, tư vấn nhiệt tình",
    "items": [
      {
        "name": "Nguyen Viet Dung",
        "description": "Quá trình làm không hề đau đớn, bác sĩ làm rất êm tay nên tôi cảm thấy dễ chịu, không “khủng khiếp” như những gì tôi đã tưởng tượng trước đó.",
        "icon": "/assets/images/nguyen_viet_dung.jpg"
      },
      {
        "name": "Nguyễn Thị Cẩm Vân",
        "description": "Bác sĩ tư vấn kỹ càng, chu đáo, tư vấn phương án điều trị hợp lý với tài chính, hướng dẫn chăm sóc răng miệng rất nhiệt tình.",
        "icon": "/assets/images/nguyen_thi_cam_v.jpg"
      },
      {
        "name": "Hoàng Thảo Nguyên",
        "description": "Nhờ thẩm mỹ răng sứ tại Nha Khoa Cao Kỳ, em tự tin cười tỏa sáng và sức khỏe răng miệng ngày càng cải thiện.",
        "icon": "/assets/images/hoang_thao_nguyen.jpg"
      },
      {
        "name": "Hằng Nguyễn",
        "description": "Phụ nữ ai cũng có nhu cầu làm đẹp, trước đây mình không tự tin với hàm răng ố vàng của mình, nhưng giờ thì nụ cười đã tỏa sáng hơn nhiều nhờ bác sĩ Kỳ rồi.",
        "icon": "/assets/images/v.jpg"
      }
    ]
  },
  "pricing": {
    "title": "Dịch vụ",
    "items": [
      {
        "name": "Điều trị tủy",
        "price": "$0",
        "priceDetails": "for one user",
        "features": [
          "1 user",
          "Basic Support",
          "1 GB of storage",
          "Email support"
        ]
      },
      {
        "name": "Niềng răng",
        "price": "$15",
        "priceDetails": "per user",

        "features": [
          "5 users",
          "Priority Support",
          "10 GB of storage",
          "Phone and Email support"
        ]
      },
      {
        "name": "Phẫu thuật cắt lợi",
        "price": "$29",
        "priceDetails": "per user",
        "features": [
          "50 users",
          "24/7 Support",
          "100 GB of storage",
          "Phone and Email support"
        ]
      }
    ]
  },
  "about": {
    "sections": [
      {
        "name": "Nha Khoa Cao Kỳ",
        "href": "#",
        "content": "It is a long established fact that a reader will be distracted by the readable content of a page when looking at its layout. The point of using Lorem Ipsum is that it has a more-or-less normal distribution of letters, as opposed to using 'Content here, content here', making it look like readable English."
      },
      {
        "name": "Uy tín",
        "href": "#",
        "content": "It is a long established fact that a reader will be distracted by the readable content of a page when looking at its layout. The point of using Lorem Ipsum is that it has a more-or-less normal distribution of letters, as opposed to using 'Content here, content here', making it look like readable English."
      },
      {
        "name": "Trách nhiệm",
        "href": "#",
        "content": "It is a long established fact that a reader will be distracted by the readable content of a page when looking at its layout. The point of using Lorem Ipsum is that it has a more-or-less normal distribution of letters, as opposed to using 'Content here, content here', making it look like readable English."
      },
      {
        "name": "Tận tâm",
        "href": "#",
        "content": "It is a long established fact that a reader will be distracted by the readable content of a page when looking at its layout. The point of using Lorem Ipsum is that it has a more-or-less normal distribution of letters, as opposed to using 'Content here, content here', making it look like readable English."
      }
    ],
    "socialMedia": {
      "facebook": "https://www.facebook.com/ky.sniper",
      "zalo": "https://zalo.me/0975115379",
      "contact": "tel:0975115379"
    }
  }
}
